setup.py
fancyhands/__init__.py
fancyhands.egg-info/PKG-INFO
fancyhands.egg-info/SOURCES.txt
fancyhands.egg-info/dependency_links.txt
fancyhands.egg-info/requires.txt
fancyhands.egg-info/top_level.txt