Metadata-Version: 1.0
Name: fancyhands
Version: 1.1
Summary: fancyhands.com python API
Home-page: https://github.com/fancyhands/fancyhands-python
Author: Fancy Hands
Author-email: api@fancyhands.com
License: MIT
Platform: UNKNOWN
